sumdir-1.0.2.dist-info/METADATA
sumdir-1.0.2.dist-info/WHEEL
sumdir-1.0.2.dist-info/entry_points.txt
sumdir/__init__.py
sumdir/__version__.py
sumdir/main.py
sumdir-1.0.2.dist-info/RECORD
