Metadata-Version: 2.1
Name: sumdir
Version: 1.0.2
Summary: Display sizes of the current subdirectories
Author-Email: rmm <rosa.martinez@artgins.com>
License: MIT
Requires-Python: >=3.7
Requires-Dist: typer[all]>=0.9.0
